ovos_number_parser/__init__.py
ovos_number_parser/numbers_az.py
ovos_number_parser/numbers_ca.py
ovos_number_parser/numbers_cs.py
ovos_number_parser/numbers_da.py
ovos_number_parser/numbers_de.py
ovos_number_parser/numbers_en.py
ovos_number_parser/numbers_es.py
ovos_number_parser/numbers_eu.py
ovos_number_parser/numbers_fa.py
ovos_number_parser/numbers_fr.py
ovos_number_parser/numbers_gl.py
ovos_number_parser/numbers_hu.py
ovos_number_parser/numbers_it.py
ovos_number_parser/numbers_mwl.py
ovos_number_parser/numbers_nl.py
ovos_number_parser/numbers_pl.py
ovos_number_parser/numbers_pt.py
ovos_number_parser/numbers_ru.py
ovos_number_parser/numbers_sl.py
ovos_number_parser/numbers_sv.py
ovos_number_parser/numbers_uk.py
ovos_number_parser/util.py
ovos_number_parser/version.py
ovos_number_parser-0.5.1.dist-info/METADATA
ovos_number_parser-0.5.1.dist-info/WHEEL
ovos_number_parser-0.5.1.dist-info/top_level.txt
ovos_number_parser-0.5.1.dist-info/RECORD
