Metadata-Version: 2.1
Name: ovos-number-parser
Version: 0.5.1
Summary: OpenVoiceOS's multilingual text parsing and formatting library
Home-page: https://github.com/OpenVoiceOS/ovos-number-parser
Author: Mycroft AI / OVOS
Author-email: jarbasai@mailfence.com
License: Apache2.0
Classifier: Development Status :: 4 - Beta
Classifier: Intended Audience :: Developers
Classifier: Topic :: Text Processing :: Linguistic
Classifier: License :: OSI Approved :: Apache Software License
Classifier: Programming Language :: Python :: 3.6
Classifier: Programming Language :: Python :: 3.7
Classifier: Programming Language :: Python :: 3.8
Classifier: Programming Language :: Python :: 3.9
Requires-Dist: quebra-frases>=0.3.7
Requires-Dist: unicode-rbnf
